{
"INTERPOLATE_RELPERM" : {
"INTERPOLATE_GO" : -0.762742,
"INTERPOLATE_WO" : -0.710036
},
"LOG10_MULTFLT" : {
"MULTFLT_F1" : -0.146882,
"MULTFLT_F2" : -2.80479,
"MULTFLT_F3" : -0.160463,
"MULTFLT_F4" : -2.59951,
"MULTFLT_F5" : -3.70738
},
"LOG10_MULTZ" : {
"MULTZ_MIDREEK" : -6.41989
},
"MULTFLT" : {
"MULTFLT_F1" : 0.713047,
"MULTFLT_F2" : 0.00156749,
"MULTFLT_F3" : 0.691094,
"MULTFLT_F4" : 0.0025147,
"MULTFLT_F5" : 0.000196163
},
"MULTZ" : {
"MULTZ_MIDREEK" : 3.80283e-07
},
"RMSGLOBPARAMS" : {
"COHIBA_MODEL_MODE" : 1,
"FWL" : 1702.48
},
"INTERPOLATE_RELPERM:INTERPOLATE_GO" : -0.762742,
"INTERPOLATE_RELPERM:INTERPOLATE_WO" : -0.710036,
"LOG10_MULTFLT:MULTFLT_F1" : -0.146882,
"LOG10_MULTFLT:MULTFLT_F2" : -2.80479,
"LOG10_MULTFLT:MULTFLT_F3" : -0.160463,
"LOG10_MULTFLT:MULTFLT_F4" : -2.59951,
"LOG10_MULTFLT:MULTFLT_F5" : -3.70738,
"LOG10_MULTZ:MULTZ_MIDREEK" : -6.41989,
"MULTFLT:MULTFLT_F1" : 0.713047,
"MULTFLT:MULTFLT_F2" : 0.00156749,
"MULTFLT:MULTFLT_F3" : 0.691094,
"MULTFLT:MULTFLT_F4" : 0.0025147,
"MULTFLT:MULTFLT_F5" : 0.000196163,
"MULTZ:MULTZ_MIDREEK" : 3.80283e-07,
"RMSGLOBPARAMS:COHIBA_MODEL_MODE" : 1,
"RMSGLOBPARAMS:FWL" : 1702.48
}
