{
"INTERPOLATE_RELPERM" : {
"INTERPOLATE_GO" : -0.852241,
"INTERPOLATE_WO" : -0.984478
},
"LOG10_MULTFLT" : {
"MULTFLT_F1" : -0.179441,
"MULTFLT_F2" : -0.554874,
"MULTFLT_F3" : -0.483344,
"MULTFLT_F4" : -2.73062,
"MULTFLT_F5" : -1.20993
},
"LOG10_MULTZ" : {
"MULTZ_MIDREEK" : -2.92897
},
"MULTFLT" : {
"MULTFLT_F1" : 0.661545,
"MULTFLT_F2" : 0.278693,
"MULTFLT_F3" : 0.328591,
"MULTFLT_F4" : 0.00185942,
"MULTFLT_F5" : 0.0616697
},
"MULTZ" : {
"MULTZ_MIDREEK" : 0.00117769
},
"RMSGLOBPARAMS" : {
"COHIBA_MODEL_MODE" : 1,
"FWL" : 1704.28
},
"INTERPOLATE_RELPERM:INTERPOLATE_GO" : -0.852241,
"INTERPOLATE_RELPERM:INTERPOLATE_WO" : -0.984478,
"LOG10_MULTFLT:MULTFLT_F1" : -0.179441,
"LOG10_MULTFLT:MULTFLT_F2" : -0.554874,
"LOG10_MULTFLT:MULTFLT_F3" : -0.483344,
"LOG10_MULTFLT:MULTFLT_F4" : -2.73062,
"LOG10_MULTFLT:MULTFLT_F5" : -1.20993,
"LOG10_MULTZ:MULTZ_MIDREEK" : -2.92897,
"MULTFLT:MULTFLT_F1" : 0.661545,
"MULTFLT:MULTFLT_F2" : 0.278693,
"MULTFLT:MULTFLT_F3" : 0.328591,
"MULTFLT:MULTFLT_F4" : 0.00185942,
"MULTFLT:MULTFLT_F5" : 0.0616697,
"MULTZ:MULTZ_MIDREEK" : 0.00117769,
"RMSGLOBPARAMS:COHIBA_MODEL_MODE" : 1,
"RMSGLOBPARAMS:FWL" : 1704.28
}
