{
"INTERPOLATE_RELPERM" : {
"INTERPOLATE_GO" : -0.383043,
"INTERPOLATE_WO" : -0.993925
},
"LOG10_MULTFLT" : {
"MULTFLT_F1" : -0.528465,
"MULTFLT_F2" : -1.72033,
"MULTFLT_F3" : -0.537522,
"MULTFLT_F4" : -2.98619,
"MULTFLT_F5" : -1.22386
},
"LOG10_MULTZ" : {
"MULTZ_MIDREEK" : -1.90141
},
"MULTFLT" : {
"MULTFLT_F1" : 0.296166,
"MULTFLT_F2" : 0.01904,
"MULTFLT_F3" : 0.290054,
"MULTFLT_F4" : 0.0010323,
"MULTFLT_F5" : 0.0597229
},
"MULTZ" : {
"MULTZ_MIDREEK" : 0.0125483
},
"RMSGLOBPARAMS" : {
"COHIBA_MODEL_MODE" : 1,
"FWL" : 1704.5
},
"INTERPOLATE_RELPERM:INTERPOLATE_GO" : -0.383043,
"INTERPOLATE_RELPERM:INTERPOLATE_WO" : -0.993925,
"LOG10_MULTFLT:MULTFLT_F1" : -0.528465,
"LOG10_MULTFLT:MULTFLT_F2" : -1.72033,
"LOG10_MULTFLT:MULTFLT_F3" : -0.537522,
"LOG10_MULTFLT:MULTFLT_F4" : -2.98619,
"LOG10_MULTFLT:MULTFLT_F5" : -1.22386,
"LOG10_MULTZ:MULTZ_MIDREEK" : -1.90141,
"MULTFLT:MULTFLT_F1" : 0.296166,
"MULTFLT:MULTFLT_F2" : 0.01904,
"MULTFLT:MULTFLT_F3" : 0.290054,
"MULTFLT:MULTFLT_F4" : 0.0010323,
"MULTFLT:MULTFLT_F5" : 0.0597229,
"MULTZ:MULTZ_MIDREEK" : 0.0125483,
"RMSGLOBPARAMS:COHIBA_MODEL_MODE" : 1,
"RMSGLOBPARAMS:FWL" : 1704.5
}
