{
"INTERPOLATE_RELPERM" : {
"INTERPOLATE_GO" : -0.721295,
"INTERPOLATE_WO" : -0.955132
},
"LOG10_MULTFLT" : {
"MULTFLT_F1" : -0.570246,
"MULTFLT_F2" : -0.433705,
"MULTFLT_F3" : -0.665689,
"MULTFLT_F4" : -2.98266,
"MULTFLT_F5" : -1.33501
},
"LOG10_MULTZ" : {
"MULTZ_MIDREEK" : -1.45668
},
"MULTFLT" : {
"MULTFLT_F1" : 0.269001,
"MULTFLT_F2" : 0.368379,
"MULTFLT_F3" : 0.215929,
"MULTFLT_F4" : 0.00104072,
"MULTFLT_F5" : 0.0462372
},
"MULTZ" : {
"MULTZ_MIDREEK" : 0.0349396
},
"RMSGLOBPARAMS" : {
"COHIBA_MODEL_MODE" : 1,
"FWL" : 1704.58
},
"INTERPOLATE_RELPERM:INTERPOLATE_GO" : -0.721295,
"INTERPOLATE_RELPERM:INTERPOLATE_WO" : -0.955132,
"LOG10_MULTFLT:MULTFLT_F1" : -0.570246,
"LOG10_MULTFLT:MULTFLT_F2" : -0.433705,
"LOG10_MULTFLT:MULTFLT_F3" : -0.665689,
"LOG10_MULTFLT:MULTFLT_F4" : -2.98266,
"LOG10_MULTFLT:MULTFLT_F5" : -1.33501,
"LOG10_MULTZ:MULTZ_MIDREEK" : -1.45668,
"MULTFLT:MULTFLT_F1" : 0.269001,
"MULTFLT:MULTFLT_F2" : 0.368379,
"MULTFLT:MULTFLT_F3" : 0.215929,
"MULTFLT:MULTFLT_F4" : 0.00104072,
"MULTFLT:MULTFLT_F5" : 0.0462372,
"MULTZ:MULTZ_MIDREEK" : 0.0349396,
"RMSGLOBPARAMS:COHIBA_MODEL_MODE" : 1,
"RMSGLOBPARAMS:FWL" : 1704.58
}
