{
"INTERPOLATE_RELPERM" : {
"INTERPOLATE_GO" : -0.221783,
"INTERPOLATE_WO" : -0.981493
},
"LOG10_MULTFLT" : {
"MULTFLT_F1" : -0.346128,
"MULTFLT_F2" : -1.84969,
"MULTFLT_F3" : -0.23235,
"MULTFLT_F4" : -3.84497,
"MULTFLT_F5" : -2.45896
},
"LOG10_MULTZ" : {
"MULTZ_MIDREEK" : -4.84314
},
"MULTFLT" : {
"MULTFLT_F1" : 0.450684,
"MULTFLT_F2" : 0.0141355,
"MULTFLT_F3" : 0.585666,
"MULTFLT_F4" : 0.000142898,
"MULTFLT_F5" : 0.00347568
},
"MULTZ" : {
"MULTZ_MIDREEK" : 1.43502e-05
},
"RMSGLOBPARAMS" : {
"COHIBA_MODEL_MODE" : 1,
"FWL" : 1702.41
},
"INTERPOLATE_RELPERM:INTERPOLATE_GO" : -0.221783,
"INTERPOLATE_RELPERM:INTERPOLATE_WO" : -0.981493,
"LOG10_MULTFLT:MULTFLT_F1" : -0.346128,
"LOG10_MULTFLT:MULTFLT_F2" : -1.84969,
"LOG10_MULTFLT:MULTFLT_F3" : -0.23235,
"LOG10_MULTFLT:MULTFLT_F4" : -3.84497,
"LOG10_MULTFLT:MULTFLT_F5" : -2.45896,
"LOG10_MULTZ:MULTZ_MIDREEK" : -4.84314,
"MULTFLT:MULTFLT_F1" : 0.450684,
"MULTFLT:MULTFLT_F2" : 0.0141355,
"MULTFLT:MULTFLT_F3" : 0.585666,
"MULTFLT:MULTFLT_F4" : 0.000142898,
"MULTFLT:MULTFLT_F5" : 0.00347568,
"MULTZ:MULTZ_MIDREEK" : 1.43502e-05,
"RMSGLOBPARAMS:COHIBA_MODEL_MODE" : 1,
"RMSGLOBPARAMS:FWL" : 1702.41
}
